LICENSE
README.md
setup.cfg
setup.py
prisma_configure_mesh.egg-info/PKG-INFO
prisma_configure_mesh.egg-info/SOURCES.txt
prisma_configure_mesh.egg-info/dependency_links.txt
prisma_configure_mesh.egg-info/entry_points.txt
prisma_configure_mesh.egg-info/requires.txt
prisma_configure_mesh.egg-info/top_level.txt
prisma_mesh_functions/__init__.py
prisma_mesh_functions/anynets.py
prisma_mesh_functions/menus.py
prisma_mesh_functions/sites.py
prisma_mesh_functions/utils.py
prisma_mesh_functions/versions.py
prisma_mesh_functions/vpn.py