Metadata-Version: 2.1
Name: prisma-configure-mesh
Version: 1.1.0b1
Summary: Utility for changing from Hub/Spoke to Regional, Full, or Custom Mesh for Prisma SD-WAN.
Home-page: https://github.com/ebob9/prisma_configure_mesh
Author: Aaron Edwards
Author-email: prisma_configure_mesh@ebob9.com
License: MIT
Classifier: Development Status :: 4 - Beta
Classifier: Intended Audience :: Developers
Classifier: License :: OSI Approved :: MIT License
Classifier: Programming Language :: Python :: 3.7
Classifier: Programming Language :: Python :: 3.8
Classifier: Programming Language :: Python :: 3.9
Classifier: Programming Language :: Python :: 3.10
License-File: LICENSE
